{
    "name": "Stacked_Mining",
    "version": "2.0.1",
    "factorio_version": "2.0",
    "title": "Deadlock's Stacked Mining",
    "author": "Kythblood (updated by billbo99)",
    "dependencies": [
        "base",
        "deadlock-beltboxes-loaders",
        "? maraxsis",
        "? planet-arrakis",
        "? planet-muluna",
        "? IndustrialRevolutionStacking",
        "? CompressedFluids",
        "? Krastorio2",
        "? steinios_unlasting_oil",
        "? angelsinfiniteores",
        "? angelsrefining",
        "? pycoalprocessing",
        "? pyfusionenergy",
        "? pyhightech",
        "? pyindustry",
        "? pypetroleumhandling",
        "? pyrawores",
        "? IndustrialRevolutionStacking",
        "? DeadlockStackingForExoticIndustries",
        "? Deadlock-SE-bridge",
        "? FactorioExtended-Plus-Transport"
    ],
    "description": "Adds a mining planner that allows you to mark ores to be mined directly as their stacked version.\nWith Compressed Fluids installed, resources can also be marked to be extracted as their high-pressure version."
}